gepaco/__init__.py
gepaco/__main__.py
gepaco/protocol_parser.py
gepaco/server.py
gepaco/static/favicon.png
gepaco/static/flutter_service_worker.js
gepaco/static/index.html
gepaco/static/main.dart.js
gepaco/static/manifest.json
gepaco/static/version.json
gepaco/static/assets/AssetManifest.json
gepaco/static/assets/FontManifest.json
gepaco/static/assets/NOTICES
gepaco/static/assets/fonts/MaterialIcons-Regular.otf
gepaco/static/assets/packages/cupertino_icons/assets/CupertinoIcons.ttf
gepaco/static/canvaskit/canvaskit.js
gepaco/static/canvaskit/canvaskit.wasm
gepaco/static/canvaskit/profiling/canvaskit.js
gepaco/static/canvaskit/profiling/canvaskit.wasm
gepaco/static/icons/Icon-192.png
gepaco/static/icons/Icon-512.png
gepaco/static/icons/Icon-maskable-192.png
gepaco/static/icons/Icon-maskable-512.png
gpc/__init__.py
gpc/__main__.py
gpc/protocol_parser.py
gpc/server.py
gpc/static/favicon.png
gpc/static/flutter_service_worker.js
gpc/static/index.html
gpc/static/main.dart.js
gpc/static/manifest.json
gpc/static/version.json
gpc/static/assets/AssetManifest.json
gpc/static/assets/FontManifest.json
gpc/static/assets/NOTICES
gpc/static/assets/fonts/MaterialIcons-Regular.otf
gpc/static/assets/packages/cupertino_icons/assets/CupertinoIcons.ttf
gpc/static/canvaskit/canvaskit.js
gpc/static/canvaskit/canvaskit.wasm
gpc/static/canvaskit/profiling/canvaskit.js
gpc/static/canvaskit/profiling/canvaskit.wasm
gpc/static/icons/Icon-192.png
gpc/static/icons/Icon-512.png
gpc/static/icons/Icon-maskable-192.png
gpc/static/icons/Icon-maskable-512.png
gpc/static/web/.last_build_id
gpc/static/web/favicon.png
gpc/static/web/flutter_service_worker.js
gpc/static/web/index.html
gpc/static/web/main.dart.js
gpc/static/web/manifest.json
gpc/static/web/version.json
gpc/static/web/assets/AssetManifest.json
gpc/static/web/assets/FontManifest.json
gpc/static/web/assets/NOTICES
gpc/static/web/assets/fonts/MaterialIcons-Regular.otf
gpc/static/web/assets/packages/cupertino_icons/assets/CupertinoIcons.ttf
gepaco-0.0.1.dist-info/METADATA
gepaco-0.0.1.dist-info/WHEEL
gepaco-0.0.1.dist-info/entry_points.txt
gepaco-0.0.1.dist-info/top_level.txt
gepaco-0.0.1.dist-info/RECORD
